README.md
setup.py
python_translate/__init__.py
python_translate/dumpers.py
python_translate/glue.py
python_translate/loaders.py
python_translate/operations.py
python_translate/selector.py
python_translate/translations.py
python_translate/utils.py
python_translate.egg-info/PKG-INFO
python_translate.egg-info/SOURCES.txt
python_translate.egg-info/dependency_links.txt
python_translate.egg-info/pbr.json
python_translate.egg-info/requires.txt
python_translate.egg-info/top_level.txt
python_translate/extractors/__init__.py
python_translate/extractors/base.py
python_translate/extractors/python.py
python_translate/tests/IntervalTest.py
python_translate/tests/MessageCatalogueTest.py
python_translate/tests/MessageSelectorTest.py
python_translate/tests/PluralizationRulesTest.py
python_translate/tests/TranslatorTest.py
python_translate/tests/__init__.py
python_translate/tests/dumpers/JSONFileDumperTest.py
python_translate/tests/dumpers/MoFileDumperTest.py
python_translate/tests/dumpers/PoFileDumperTest.py
python_translate/tests/dumpers/YamlFileDumperTest.py
python_translate/tests/dumpers/__init__.py
python_translate/tests/loaders/JSONFileLoaderTest.py
python_translate/tests/loaders/MoFileLoaderTest.py
python_translate/tests/loaders/PoFileLoaderTest.py
python_translate/tests/loaders/YamlFileLoaderTest.py
python_translate/tests/loaders/__init__.py