Metadata-Version: 1.0
Name: python-translate
Version: 1.0.15
Summary: Non-gettext translations for python.
Home-page: https://github.com/adamziel/python_translate
Author: Adam Zieliński
Author-email: adam@adamziel.com
License: MIT
Platform: UNKNOWN
